{"nodes": [{"id": "d_proyectos_sistema_sfit_sfit_app_lib_core_theme_app_radius_dart", "label": "app_radius.dart", "file_type": "code", "source_file": "D:\\Proyectos\\Sistema Sfit\\sfit-app\\lib\\core\\theme\\app_radius.dart", "source_location": null}, {"id": "d_proyectos_sistema_sfit_sfit_app_lib_core_theme_app_radius_dart_appradius", "label": "AppRadius", "file_type": "code", "source_file": "D:\\Proyectos\\Sistema Sfit\\sfit-app\\lib\\core\\theme\\app_radius.dart", "source_location": null}, {"id": "package_flutter_widgets_dart", "label": "package:flutter/widgets.dart", "file_type": "code", "source_file": "D:\\Proyectos\\Sistema Sfit\\sfit-app\\lib\\core\\theme\\app_radius.dart", "source_location": null}], "edges": [{"source": "d_proyectos_sistema_sfit_sfit_app_lib_core_theme_app_radius_dart", "target": "d_proyectos_sistema_sfit_sfit_app_lib_core_theme_app_radius_dart_appradius", "relation": "defines", "confidence": "EXTRACTED", "confidence_score": 1.0, "source_file": "D:\\Proyectos\\Sistema Sfit\\sfit-app\\lib\\core\\theme\\app_radius.dart", "source_location": null, "weight": 1.0}, {"source": "d_proyectos_sistema_sfit_sfit_app_lib_core_theme_app_radius_dart", "target": "package_flutter_widgets_dart", "relation": "imports", "confidence": "EXTRACTED", "confidence_score": 1.0, "source_file": "D:\\Proyectos\\Sistema Sfit\\sfit-app\\lib\\core\\theme\\app_radius.dart", "source_location": null, "weight": 1.0}]}